Workbook

Sheet Stock_Data
A1: NSE ALPHA SCREENER — Stock Universe Data (Dec 2024)
A2: # | B2: Company Name | C2: Ticker | D2: Sector | E2: Current Price(KES) | F2: 52-Week High(KES) | G2: 52-Week Low (KES) | H2: EPS (KES) | I2: P/E Ratio | J2: Book Value Per Share (KES) | K2: P/B Ratio | L2: Dividend Per Share (KES) | M2: Dividend Yield (%) | N2: EPS Growth YoY (%) | O2: Market Cap (KES Millions) | P2: Data Source | Q2: Momentum Ratio
B3: Equity Group Holdings | C3: EQTY | D3: Banking | E3: 42.5 | F3: 55 | G3: 38 | H3: 6.2 | I3: 6.85 | J3: 48.3 | K3: 0.88 | L3: 4 | M3: 9.41 | N3: 8.5 | O3: 160650 | P3: NSE/Investing.com | Q3: =(E3-G3)/(F3-G3) -> 0.26470588
B4: KCB Group | C4: KCB | D4: Banking | E4: 28.9 | F4: 40 | G4: 24 | H4: 7.1 | I4: 4.07 | J4: 52.1 | K4: 0.55 | L4: 2 | M4: 6.92 | N4: -5.2 | O4: 92908 | P4: NSE/Investing.com | Q4: =(E4-G4)/(F4-G4) -> 0.30625
B5: Co-operative Bank | C5: COOP | D5: Banking | E5: 13.5 | F5: 16.5 | G5: 11 | H5: 2.8 | I5: 4.82 | J5: 18.6 | K5: 0.73 | L5: 1 | M5: 7.41 | N5: 3.1 | O5: 79110 | P5: NSE/Investing.com | Q5: =(E5-G5)/(F5-G5) -> 0.45454545
B6: NCBA Group | C6: NCBA | D6: Banking | E6: 37 | F6: 42 | G6: 30 | H6: 8.3 | I6: 4.46 | J6: 44.2 | K6: 0.84 | L6: 3.25 | M6: 8.78 | N6: 11.2 | O6: 60270 | P6: NSE/Investing.com | Q6: =(E6-G6)/(F6-G6) -> 0.58333333
B7: Diamond Trust Bank | C7: DTB | D7: Banking | E7: 52 | F7: 65 | G7: 45 | H7: 18.5 | I7: 2.81 | J7: 110.4 | K7: 0.47 | L7: 3 | M7: 5.77 | N7: 2.8 | O7: 15600 | P7: NSE/Investing.com | Q7: =(E7-G7)/(F7-G7) -> 0.35
B8: Stanbic Holdings | C8: SBIC | D8: Banking | E8: 96 | F8: 115 | G8: 82 | H8: 16.2 | I8: 5.93 | J8: 75.3 | K8: 1.27 | L8: 6.5 | M8: 6.77 | N8: 14.3 | O8: 38400 | P8: NSE/Investing.com | Q8: =(E8-G8)/(F8-G8) -> 0.42424242
B9: Standard Chartered | C9: SCBK | D9: Banking | E9: 175 | F9: 210 | G9: 150 | H9: 28.4 | I9: 6.16 | J9: 148 | K9: 1.18 | L9: 18 | M9: 10.29 | N9: 6.7 | O9: 66500 | P9: NSE/Investing.com | Q9: =(E9-G9)/(F9-G9) -> 0.41666667
B10: Safaricom PLC | C10: SCOM | D10: Telco | E10: 16.2 | F10: 22 | G10: 13.5 | H10: 1.32 | I10: 12.27 | J10: 5.4 | K10: 3 | L10: 0.67 | M10: 4.14 | N10: -18.5 | O10: 648000 | P10: NSE/Investing.com | Q10: =(E10-G10)/(F10-G10) -> 0.31764706
B11: Jubilee Holdings | C11: JUB | D11: Insurance | E11: 195 | F11: 230 | G11: 170 | H11: 31.5 | I11: 6.19 | J11: 220 | K11: 0.89 | L11: 9 | M11: 4.62 | N11: 5.3 | O11: 17550 | P11: NSE/Investing.com | Q11: =(E11-G11)/(F11-G11) -> 0.41666667
B12: Britam Holdings | C12: BRIT | D12: Insurance | E12: 5.8 | F12: 8 | G12: 4.9 | H12: 0.62 | I12: 9.35 | J12: 9.8 | K12: 0.59 | L12: 0.2 | M12: 3.45 | N12: -12.4 | O12: 15109 | P12: NSE/Investing.com | Q12: =(E12-G12)/(F12-G12) -> 0.29032258
B13: CIC Insurance | C13: CIC | D13: Insurance | E13: 2.25 | F13: 3.1 | G13: 1.9 | H13: 0.18 | I13: 12.5 | J13: 3.2 | K13: 0.7 | L13: 0.05 | M13: 2.22 | N13: 1.8 | O13: 7425 | P13: NSE/Investing.com | Q13: =(E13-G13)/(F13-G13) -> 0.29166667
B14: Kenya Reinsurance | C14: KNRE | D14: Insurance | E14: 2.3 | F14: 3 | G14: 1.9 | H14: 0.55 | I14: 4.18 | J14: 5.4 | K14: 0.43 | L14: 0.2 | M14: 8.7 | N14: 4.5 | O14: 6831 | P14: NSE/Investing.com | Q14: =(E14-G14)/(F14-G14) -> 0.36363636
... B27: Bamburi Cement | C27: BAMB | D27: Manufacturing | E27: 45 | F27: 65 | G27: 38 | H27: 6.1 | I27: 7.38 | J27: 38 | K27: 1.18 | L27: 3.5 | M27: 7.78 | N27: -9.3 | O27: 16290 | P27: NSE/Investing.com | Q27: =(E27-G27)/(F27-G27) -> 0.25925926

Sheet Screener
A1: NSE ALPHA SCREENER — Stock Scoring Model (Dec 2024)
B2: Top Ranked Stock: | C2: =INDEX(B7:B31,MATCH(1,K7:K31,0)) -> I&M Holdings
B3: Highest Score: | C3: =MAX(J7:J31) -> 91.465
B4: Average Score: | C4: =AVERAGE(J7:J31) -> 53.1828
B5: Stocks Rated "Buy"+: | C5: =COUNTIF(L7:L31,"*Buy*") -> 10
A6: # | B6: Company Name | C6: Ticker | D6: Sector | E6: P/E Score (25%) | F6: Div Yield Score (20%) | G6: EPS Growth Score (20%) | H6: P/B Score (20%) | I6: Momentum Score (15%) | J6: COMPOSITE SCORE | K6: RANK | L6: RATING
A7: 1 | B7: =Stock_Data!B3 -> Equity Group Holdings | C7: =Stock_Data!C3 -> EQTY | D7: =Stock_Data!D3 -> Banking | E7: =(1-PERCENTRANK(Stock_Data!I3:I27,Stock_Data!I3))*100 -> 45.9 | F7: =PERCENTRANK(Stock_Data!M3:M27,Stock_Data!M3)*100 -> 87.5 | G7: =PERCENTRANK(Stock_Data!N3:N27,Stock_Data!N3)*100 -> 79.1 | H7: =(1-PERCENTRANK(Stock_Data!K3:K27,Stock_Data!K3))*100 -> 41.7 | I7: =PERCENTRANK(Stock_Data!$Q$3:$Q$27,Stock_Data!Q3)*100 -> 12.5 | J7: =(E7*0.25)+(F7*0.2)+(G7*0.2)+(H7*0.2)+(I7*0.15) -> 55.01 | K7: =RANK(J7,$J$7:$J$31,0) -> 13 | L7: {=_xlfn.IFS(J7>=75," Strong Buy",J7>=60," Buy",J7>=45,"Hold",J7>=30," Underperform",J7<30,"Avoid")} -> Hold
A8: 2 | B8: =Stock_Data!B4 -> KCB Group | C8: =Stock_Data!C4 -> KCB | D8: =Stock_Data!D4 -> Banking | E8: =(1-PERCENTRANK(Stock_Data!I4:I28,Stock_Data!I4))*100 -> 87 | F8: =PERCENTRANK(Stock_Data!M4:M28,Stock_Data!M4)*100 -> 47.8 | G8: =PERCENTRANK(Stock_Data!N4:N28,Stock_Data!N4)*100 -> 30.4 | H8: =(1-PERCENTRANK(Stock_Data!K4:K28,Stock_Data!K4))*100 -> 78.3 | I8: =PERCENTRANK(Stock_Data!$Q$3:$Q$27,Stock_Data!Q4)*100 -> 29.1 | J8: =(E8*0.25)+(F8*0.2)+(G8*0.2)+(H8*0.2)+(I8*0.15) -> 57.415 | K8: =RANK(J8,$J$7:$J$31,0) -> 12 | L8: {=_xlfn.IFS(J8>=75," Strong Buy",J8>=60," Buy",J8>=45,"Hold",J8>=30," Underperform",J8<30,"Avoid")} -> Hold
A9: 3 | B9: =Stock_Data!B5 -> Co-operative Bank | C9: =Stock_Data!C5 -> COOP | D9: =Stock_Data!D5 -> Banking | E9: =(1-PERCENTRANK(Stock_Data!I5:I29,Stock_Data!I5))*100 -> 72.8 | F9: =PERCENTRANK(Stock_Data!M5:M29,Stock_Data!M5)*100 -> 54.5 | G9: =PERCENTRANK(Stock_Data!N5:N29,Stock_Data!N5)*100 -> 50 | H9: =(1-PERCENTRANK(Stock_Data!K5:K29,Stock_Data!K5))*100 -> 63.7 | I9: =PERCENTRANK(Stock_Data!$Q$3:$Q$27,Stock_Data!Q5)*100 -> 91.6 | J9: =(E9*0.25)+(F9*0.2)+(G9*0.2)+(H9*0.2)+(I9*0.15) -> 65.58 | K9: =RANK(J9,$J$7:$J$31,0) -> 8 | L9: {=_xlfn.IFS(J9>=75," Strong Buy",J9>=60," Buy",J9>=45,"Hold",J9>=30," Underperform",J9<30,"Avoid")} -> Buy
A10: 4 | B10: =Stock_Data!B6 -> NCBA Group | C10: =Stock_Data!C6 -> NCBA | D10: =Stock_Data!D6 -> Banking | E10: =(1-PERCENTRANK(Stock_Data!I6:I30,Stock_Data!I6))*100 -> 76.2 | F10: =PERCENTRANK(Stock_Data!M6:M30,Stock_Data!M6)*100 -> 85.7 | G10: =PERCENTRANK(Stock_Data!N6:N30,Stock_Data!N6)*100 -> 90.4 | H10: =(1-PERCENTRANK(Stock_Data!K6:K30,Stock_Data!K6))*100 -> 52.4 | I10: =PERCENTRANK(Stock_Data!$Q$3:$Q$27,Stock_Data!Q6)*100 -> 100 | J10: =(E10*0.25)+(F10*0.2)+(G10*0.2)+(H10*0.2)+(I10*0.15) -> 79.75 | K10: =RANK(J10,$J$7:$J$31,0) -> 2 | L10: {=_xlfn.IFS(J10>=75," Strong Buy",J10>=60," Buy",J10>=45,"Hold",J10>=30," Underperform",J10<30,"Avoid")} -> Strong Buy
A11: 5 | B11: =Stock_Data!B7 -> Diamond Trust Bank | C11: =Stock_Data!C7 -> DTB | D11: =Stock_Data!D7 -> Banking | E11: =(1-PERCENTRANK(Stock_Data!I7:I31,Stock_Data!I7))*100 -> 95 | F11: =PERCENTRANK(Stock_Data!M7:M31,Stock_Data!M7)*100 -> 45 | G11: =PERCENTRANK(Stock_Data!N7:N31,Stock_Data!N7)*100 -> 50 | H11: =(1-PERCENTRANK(Stock_Data!K7:K31,Stock_Data!K7))*100 -> 85 | I11: =PERCENTRANK(Stock_Data!$Q$3:$Q$27,Stock_Data!Q7)*100 -> 45.8 | J11: =(E11*0.25)+(F11*0.2)+(G11*0.2)+(H11*0.2)+(I11*0.15) -> 66.62 | K11: =RANK(J11,$J$7:$J$31,0) -> 6 | L11: {=_xlfn.IFS(J11>=75," Strong Buy",J11>=60," Buy",J11>=45,"Hold",J11>=30," Underperform",J11<30,"Avoid")} -> Buy
A12: 6 | B12: =Stock_Data!B8 -> Stanbic Holdings | C12: =Stock_Data!C8 -> SBIC | D12: =Stock_Data!D8 -> Banking | E12: =(1-PERCENTRANK(Stock_Data!I8:I32,Stock_Data!I8))*100 -> 73.7 | F12: =PERCENTRANK(Stock_Data!M8:M32,Stock_Data!M8)*100 -> 47.3 | G12: =PERCENTRANK(Stock_Data!N8:N32,Stock_Data!N8)*100 -> 100 | H12: =(1-PERCENTRANK(Stock_Data!K8:K32,Stock_Data!K8))*100 -> 15.8 | I12: =PERCENTRANK(Stock_Data!$Q$3:$Q$27,Stock_Data!Q8)*100 -> 75 | J12: =(E12*0.25)+(F12*0.2)+(G12*0.2)+(H12*0.2)+(I12*0.15) -> 62.295 | K12: =RANK(J12,$J$7:$J$31,0) -> 9 | L12: {=_xlfn.IFS(J12>=75," Strong Buy",J12>=60," Buy",J12>=45,"Hold",J12>=30," Underperform",J12<30,"Avoid")} -> Buy
A13: 7 | B13: =Stock_Data!B9 -> Standard Chartered | C13: =Stock_Data!C9 -> SCBK | D13: =Stock_Data!D9 -> Banking | E13: =(1-PERCENTRANK(Stock_Data!I9:I33,Stock_Data!I9))*100 -> 72.3 | F13: =PERCENTRANK(Stock_Data!M9:M33,Stock_Data!M9)*100 -> 88.8 | G13: =PERCENTRANK(Stock_Data!N9:N33,Stock_Data!N9)*100 -> 77.7 | H13: =(1-PERCENTRANK(Stock_Data!K9:K33,Stock_Data!K9))*100 -> 22.3 | I13: =PERCENTRANK(Stock_Data!$Q$3:$Q$27,Stock_Data!Q9)*100 -> 66.6 | J13: =(E13*0.25)+(F13*0.2)+(G13*0.2)+(H13*0.2)+(I13*0.15) -> 65.825 | K13: =RANK(J13,$J$7:$J$31,0) -> 7 | L13: {=_xlfn.IFS(J13>=75," Strong Buy",J13>=60," Buy",J13>=45,"Hold",J13>=30," Underperform",J13<30,"Avoid")} -> Buy
A14: 8 | B14: =Stock_Data!B10 -> Safaricom PLC | C14: =Stock_Data!C10 -> SCOM | D14: =Stock_Data!D10 -> Telco | E14: =(1-PERCENTRANK(Stock_Data!I10:I34,Stock_Data!I10))*100 -> 11.8 | F14: =PERCENTRANK(Stock_Data!M10:M34,Stock_Data!M10)*100 -> 29.4 | G14: =PERCENTRANK(Stock_Data!N10:N34,Stock_Data!N10)*100 -> 11.7 | H14: =(1-PERCENTRANK(Stock_Data!K10:K34,Stock_Data!K10))*100 -> 11.8 | I14: =PERCENTRANK(Stock_Data!$Q$3:$Q$27,Stock_Data!Q10)*100 -> 37.5 | J14: =(E14*0.25)+(F14*0.2)+(G14*0.2)+(H14*0.2)+(I14*0.15) -> 19.155 | K14: =RANK(J14,$J$7:$J$31,0) -> 24 | L14: {=_xlfn.IFS(J14>=75," Strong Buy",J14>=60," Buy",J14>=45,"Hold",J14>=30," Underperform",J14<30,"Avoid")} -> Avoid
A15: 9 | B15: =Stock_Data!B11 -> Jubilee Holdings | C15: =Stock_Data!C11 -> JUB | D15: =Stock_Data!D11 -> Insurance | E15: =(1-PERCENTRANK(Stock_Data!I11:I35,Stock_Data!I11))*100 -> 68.8 | F15: =PERCENTRANK(Stock_Data!M11:M35,Stock_Data!M11)*100 -> 31.2 | G15: =PERCENTRANK(Stock_Data!N11:N35,Stock_Data!N11)*100 -> 62.5 | H15: =(1-PERCENTRANK(Stock_Data!K11:K35,Stock_Data!K11))*100 -> 37.5 | I15: =PERCENTRANK(Stock_Data!$Q$3:$Q$27,Stock_Data!Q11)*100 -> 66.6 | J15: =(E15*0.25)+(F15*0.2)+(G15*0.2)+(H15*0.2)+(I15*0.15) -> 53.43 | K15: =RANK(J15,$J$7:$J$31,0) -> 14 | L15: {=_xlfn.IFS(J15>=75," Strong Buy",J15>=60," Buy",J15>=45,"Hold",J15>=30," Underperform",J15<30,"Avoid")} -> Hold
A16: 10 | B16: =Stock_Data!B12 -> Britam Holdings | C16: =Stock_Data!C12 -> BRIT | D16: =Stock_Data!D12 -> Insurance | E16: =(1-PERCENTRANK(Stock_Data!I12:I36,Stock_Data!I12))*100 -> 13.4 | F16: =PERCENTRANK(Stock_Data!M12:M36,Stock_Data!M12)*100 -> 20 | G16: =PERCENTRANK(Stock_Data!N12:N36,Stock_Data!N12)*100 -> 20 | H16: =(1-PERCENTRANK(Stock_Data!K12:K36,Stock_Data!K12))*100 -> 73.4 | I16: =PERCENTRANK(Stock_Data!$Q$3:$Q$27,Stock_Data!Q12)*100 -> 20.8 | J16: =(E16*0.25)+(F16*0.2)+(G16*0.2)+(H16*0.2)+(I16*0.15) -> 29.15 | K16: =RANK(J16,$J$7:$J$31,0) -> 23 | L16: {=_xlfn.IFS(J16>=75," Strong Buy",J16>=60," Buy",J16>=45,"Hold",J16>=30," Underperform",J16<30,"Avoid")} -> Avoid
A17: 11 | B17: =Stock_Data!B13 -> CIC Insurance | C17: =Stock_Data!C13 -> CIC | D17: =Stock_Data!D13 -> Insurance | E17: =(1-PERCENTRANK(Stock_Data!I13:I37,Stock_Data!I13))*100 -> 7.2 | F17: =PERCENTRANK(Stock_Data!M13:M37,Stock_Data!M13)*100 -> 7.1 | G17: =PERCENTRANK(Stock_Data!N13:N37,Stock_Data!N13)*100 -> 42.8 | H17: =(1-PERCENTRANK(Stock_Data!K13:K37,Stock_Data!K13))*100 -> 71.5 | I17: =PERCENTRANK(Stock_Data!$Q$3:$Q$27,Stock_Data!Q13)*100 -> 25 | J17: =(E17*0.25)+(F17*0.2)+(G17*0.2)+(H17*0.2)+(I17*0.15) -> 29.83 | K17: =RANK(J17,$J$7:$J$31,0) -> 22 | L17: {=_xlfn.IFS(J17>=75," Strong Buy",J17>=60," Buy",J17>=45,"Hold",J17>=30," Underperform",J17<30,"Avoid")} -> Avoid
A18: 12 | B18: =Stock_Data!B14 -> Kenya Reinsurance | C18: =Stock_Data!C14 -> KNRE | D18: =Stock_Data!D14 -> Insurance | E18: =(1-PERCENTRANK(Stock_Data!I14:I38,Stock_Data!I14))*100 -> 84.7 | F18: =PERCENTRANK(Stock_Data!M14:M38,Stock_Data!M14)*100 -> 84.6 | G18: =PERCENTRANK(Stock_Data!N14:N38,Stock_Data!N14)*100 -> 53.8 | H18: =(1-PERCENTRANK(Stock_Data!K14:K38,Stock_Data!K14))*100 -> 92.4 | I18: =PERCENTRANK(Stock_Data!$Q$3:$Q$27,Stock_Data!Q14)*100 -> 50 | J18: =(E18*0.25)+(F18*0.2)+(G18*0.2)+(H18*0.2)+(I18*0.15) -> 74.835 | K18: =RANK(J18,$J$7:$J$31,0) -> 3 | L18: {=_xlfn.IFS(J18>=75," Strong Buy",J18>=60," Buy",J18>=45,"Hold",J18>=30," Underperform",J18<30,"Avoid")} -> Buy
... A31: 25 | B31: =Stock_Data!B27 -> Bamburi Cement | C31: =Stock_Data!C27 -> BAMB | D31: =Stock_Data!D27 -> Manufacturing | E31: =(1-PERCENTRANK(Stock_Data!I27:I51,Stock_Data!I27))*100 -> 0 | F31: =PERCENTRANK(Stock_Data!M27:M51,Stock_Data!M27)*100 -> 100 | G31: =PERCENTRANK(Stock_Data!N27:N51,Stock_Data!N27)*100 -> 100 | H31: =(1-PERCENTRANK(Stock_Data!K27:K51,Stock_Data!K27))*100 -> 0 | I31: =PERCENTRANK(Stock_Data!$Q$3:$Q$27,Stock_Data!Q27)*100 -> 8.3 | J31: =(E31*0.25)+(F31*0.2)+(G31*0.2)+(H31*0.2)+(I31*0.15) -> 41.245 | K31: =RANK(J31,$J$7:$J$31,0) -> 20 | L31: {=_xlfn.IFS(J31>=75," Strong Buy",J31>=60," Buy",J31>=45,"Hold",J31>=30," Underperform",J31<30,"Avoid")} -> Underperform

Sheet Portfolio_Sim
A1: NSE PORTFOLIO SIMULATOR - Capital Allocation Engine
A2: PORFOLIO SETTINGS
A3: Starting Capital (KES): | B3: 100000
A4: Risk-Free Rate (%): | B4: 15.5
A5: Investment Horizon (Years): | B5: 3
A6: Data As At: | B6: 45627
A9: # | B9: Stock Ticker | C9: Company Name | D9: Sector | E9: Current Price (KES) | F9: Composite Score | G9: Rating | H9: Amount Invested (KES) | I9: Allocation % | J9: Shares Purchased | K9: Current Value (KES) | L9: Dividend Income (KES) | M9: Expected Return % | N9: Weighted Return | P9: Sector | Q9: Amount
A10: 1 | B10: KCB | C10: =IFERROR(INDEX(Stock_Data!$B$3:$B$27,MATCH(B10,Stock_Data!$C$3:$C$27,0)),"") -> KCB Group | D10: =IFERROR(VLOOKUP(B10,Stock_Data!C3:D27,2,0),"") -> Banking | E10: =IFERROR(VLOOKUP(B10,Stock_Data!$C$3:$E$27,3,0),"") -> 28.9 | F10: =IFERROR(VLOOKUP(B10,Screener!$C$7:$J$31,8,0),"") -> 57.415 | G10: =IFERROR(VLOOKUP(B10,Screener!$C$7:$L$31,10,0),"") -> Hold | H10: 20000 | I10: =IFERROR(H10/SUM($H$10:$H$19),"") -> 0.056179775 | J10: =IFERROR(INT(H10/E10),"") -> 692 | K10: =IFERROR(J10*E10,"") -> 19998.8 | L10: =IFERROR(VLOOKUP(B10,Stock_Data!$C$3:$L$27,10,0)*J10,"") -> 1384 | M10: =IFERROR(VLOOKUP(B10,Stock_Data!$C$3:$M$27,11,0),"") -> 6.92 | N10: =IFERROR(I10*M10,"") -> 0.38876404 | P10: =IF(B10="","",D10) -> Banking | Q10: =IF(B10="","",H10) -> 20000
A11: 2 | B11: COOP | C11: =IFERROR(INDEX(Stock_Data!$B$3:$B$27,MATCH(B11,Stock_Data!$C$3:$C$27,0)),"") -> Co-operative Bank | D11: =IFERROR(VLOOKUP(B11,Stock_Data!C4:D28,2,0),"") -> Banking | E11: =IFERROR(VLOOKUP(B11,Stock_Data!$C$3:$E$27,3,0),"") -> 13.5 | F11: =IFERROR(VLOOKUP(B11,Screener!$C$7:$J$31,8,0),"") -> 65.58 | G11: =IFERROR(VLOOKUP(B11,Screener!$C$7:$L$31,10,0),"") -> Buy | H11: 70000 | I11: =IFERROR(H11/SUM($H$10:$H$19),"") -> 0.19662921 | J11: =IFERROR(INT(H11/E11),"") -> 5185 | K11: =IFERROR(J11*E11,"") -> 69997.5 | L11: =IFERROR(VLOOKUP(B11,Stock_Data!$C$3:$L$27,10,0)*J11,"") -> 5185 | M11: =IFERROR(VLOOKUP(B11,Stock_Data!$C$3:$M$27,11,0),"") -> 7.41 | N11: =IFERROR(I11*M11,"") -> 1.4570225 | P11: =IF(B11="","",D11) -> Banking | Q11: =IF(B11="","",H11) -> 70000
A12: 3 | B12: NCBA | C12: =IFERROR(INDEX(Stock_Data!$B$3:$B$27,MATCH(B12,Stock_Data!$C$3:$C$27,0)),"") -> NCBA Group | D12: =IFERROR(VLOOKUP(B12,Stock_Data!C5:D29,2,0),"") -> Banking | E12: =IFERROR(VLOOKUP(B12,Stock_Data!$C$3:$E$27,3,0),"") -> 37 | F12: =IFERROR(VLOOKUP(B12,Screener!$C$7:$J$31,8,0),"") -> 79.75 | G12: =IFERROR(VLOOKUP(B12,Screener!$C$7:$L$31,10,0),"") -> Strong Buy | H12: 10000 | I12: =IFERROR(H12/SUM($H$10:$H$19),"") -> 0.028089888 | J12: =IFERROR(INT(H12/E12),"") -> 270 | K12: =IFERROR(J12*E12,"") -> 9990 | L12: =IFERROR(VLOOKUP(B12,Stock_Data!$C$3:$L$27,10,0)*J12,"") -> 877.5 | M12: =IFERROR(VLOOKUP(B12,Stock_Data!$C$3:$M$27,11,0),"") -> 8.78 | N12: =IFERROR(I12*M12,"") -> 0.24662921 | P12: =IF(B12="","",D12) -> Banking | Q12: =IF(B12="","",H12) -> 10000
A13: 4 | B13: BAMB | C13: =IFERROR(INDEX(Stock_Data!$B$3:$B$27,MATCH(B13,Stock_Data!$C$3:$C$27,0)),"") -> Bamburi Cement | D13: =IFERROR(VLOOKUP(B13,Stock_Data!C6:D30,2,0),"") -> Manufacturing | E13: =IFERROR(VLOOKUP(B13,Stock_Data!$C$3:$E$27,3,0),"") -> 45 | F13: =IFERROR(VLOOKUP(B13,Screener!$C$7:$J$31,8,0),"") -> 41.245 | G13: =IFERROR(VLOOKUP(B13,Screener!$C$7:$L$31,10,0),"") -> Underperform | H13: 20000 | I13: =IFERROR(H13/SUM($H$10:$H$19),"") -> 0.056179775 | J13: =IFERROR(INT(H13/E13),"") -> 444 | K13: =IFERROR(J13*E13,"") -> 19980 | L13: =IFERROR(VLOOKUP(B13,Stock_Data!$C$3:$L$27,10,0)*J13,"") -> 1554 | M13: =IFERROR(VLOOKUP(B13,Stock_Data!$C$3:$M$27,11,0),"") -> 7.78 | N13: =IFERROR(I13*M13,"") -> 0.43707865 | P13: =IF(B13="","",D13) -> Manufacturing | Q13: =IF(B13="","",H13) -> 20000
A14: 5 | B14: KPLC | C14: =IFERROR(INDEX(Stock_Data!$B$3:$B$27,MATCH(B14,Stock_Data!$C$3:$C$27,0)),"") -> Kenya Power | D14: =IFERROR(VLOOKUP(B14,Stock_Data!C7:D31,2,0),"") -> Energy | E14: =IFERROR(VLOOKUP(B14,Stock_Data!$C$3:$E$27,3,0),"") -> 3.6 | F14: =IFERROR(VLOOKUP(B14,Screener!$C$7:$J$31,8,0),"") -> 49.795 | G14: =IFERROR(VLOOKUP(B14,Screener!$C$7:$L$31,10,0),"") -> Hold | H14: 40000 | I14: =IFERROR(H14/SUM($H$10:$H$19),"") -> 0.11235955 | J14: =IFERROR(INT(H14/E14),"") -> 11111 | K14: =IFERROR(J14*E14,"") -> 39999.6 | L14: =IFERROR(VLOOKUP(B14,Stock_Data!$C$3:$L$27,10,0)*J14,"") -> 0 | M14: =IFERROR(VLOOKUP(B14,Stock_Data!$C$3:$M$27,11,0),"") -> 0 | N14: =IFERROR(I14*M14,"") -> 0 | P14: =IF(B14="","",D14) -> Energy | Q14: =IF(B14="","",H14) -> 40000
A15: 6 | B15: BAMB | C15: =IFERROR(INDEX(Stock_Data!$B$3:$B$27,MATCH(B15,Stock_Data!$C$3:$C$27,0)),"") -> Bamburi Cement | D15: =IFERROR(VLOOKUP(B15,Stock_Data!C8:D32,2,0),"") -> Manufacturing | E15: =IFERROR(VLOOKUP(B15,Stock_Data!$C$3:$E$27,3,0),"") -> 45 | F15: =IFERROR(VLOOKUP(B15,Screener!$C$7:$J$31,8,0),"") -> 41.245 | G15: =IFERROR(VLOOKUP(B15,Screener!$C$7:$L$31,10,0),"") -> Underperform | H15: 1000 | I15: =IFERROR(H15/SUM($H$10:$H$19),"") -> 0.0028089888 | J15: =IFERROR(INT(H15/E15),"") -> 22 | K15: =IFERROR(J15*E15,"") -> 990 | L15: =IFERROR(VLOOKUP(B15,Stock_Data!$C$3:$L$27,10,0)*J15,"") -> 77 | M15: =IFERROR(VLOOKUP(B15,Stock_Data!$C$3:$M$27,11,0),"") -> 7.78 | N15: =IFERROR(I15*M15,"") -> 0.021853933 | P15: =IF(B15="","",D15) -> Manufacturing | Q15: =IF(B15="","",H15) -> 1000
A16: 7 | B16: BRIT | C16: =IFERROR(INDEX(Stock_Data!$B$3:$B$27,MATCH(B16,Stock_Data!$C$3:$C$27,0)),"") -> Britam Holdings | D16: =IFERROR(VLOOKUP(B16,Stock_Data!C9:D33,2,0),"") -> Insurance | E16: =IFERROR(VLOOKUP(B16,Stock_Data!$C$3:$E$27,3,0),"") -> 5.8 | F16: =IFERROR(VLOOKUP(B16,Screener!$C$7:$J$31,8,0),"") -> 29.15 | G16: =IFERROR(VLOOKUP(B16,Screener!$C$7:$L$31,10,0),"") -> Avoid | H16: 5000 | I16: =IFERROR(H16/SUM($H$10:$H$19),"") -> 0.014044944 | J16: =IFERROR(INT(H16/E16),"") -> 862 | K16: =IFERROR(J16*E16,"") -> 4999.6 | L16: =IFERROR(VLOOKUP(B16,Stock_Data!$C$3:$L$27,10,0)*J16,"") -> 172.4 | M16: =IFERROR(VLOOKUP(B16,Stock_Data!$C$3:$M$27,11,0),"") -> 3.45 | N16: =IFERROR(I16*M16,"") -> 0.048455056 | P16: =IF(B16="","",D16) -> Insurance | Q16: =IF(B16="","",H16) -> 5000
A17: 8 | B17: KNRE | C17: =IFERROR(INDEX(Stock_Data!$B$3:$B$27,MATCH(B17,Stock_Data!$C$3:$C$27,0)),"") -> Kenya Reinsurance | D17: =IFERROR(VLOOKUP(B17,Stock_Data!C10:D34,2,0),"") -> Insurance | E17: =IFERROR(VLOOKUP(B17,Stock_Data!$C$3:$E$27,3,0),"") -> 2.3 | F17: =IFERROR(VLOOKUP(B17,Screener!$C$7:$J$31,8,0),"") -> 74.835 | G17: =IFERROR(VLOOKUP(B17,Screener!$C$7:$L$31,10,0),"") -> Buy | H17: 50000 | I17: =IFERROR(H17/SUM($H$10:$H$19),"") -> 0.14044944 | J17: =IFERROR(INT(H17/E17),"") -> 21739 | K17: =IFERROR(J17*E17,"") -> 49999.7 | L17: =IFERROR(VLOOKUP(B17,Stock_Data!$C$3:$L$27,10,0)*J17,"") -> 4347.8 | M17: =IFERROR(VLOOKUP(B17,Stock_Data!$C$3:$M$27,11,0),"") -> 8.7 | N17: =IFERROR(I17*M17,"") -> 1.2219101 | P17: =IF(B17="","",D17) -> Insurance | Q17: =IF(B17="","",H17) -> 50000
A18: 9 | B18: JUB | C18: =IFERROR(INDEX(Stock_Data!$B$3:$B$27,MATCH(B18,Stock_Data!$C$3:$C$27,0)),"") -> Jubilee Holdings | D18: =IFERROR(VLOOKUP(B18,Stock_Data!C11:D35,2,0),"") -> Insurance | E18: =IFERROR(VLOOKUP(B18,Stock_Data!$C$3:$E$27,3,0),"") -> 195 | F18: =IFERROR(VLOOKUP(B18,Screener!$C$7:$J$31,8,0),"") -> 53.43 | G18: =IFERROR(VLOOKUP(B18,Screener!$C$7:$L$31,10,0),"") -> Hold | H18: 60000 | I18: =IFERROR(H18/SUM($H$10:$H$19),"") -> 0.16853933 | J18: =IFERROR(INT(H18/E18),"") -> 307 | K18: =IFERROR(J18*E18,"") -> 59865 | L18: =IFERROR(VLOOKUP(B18,Stock_Data!$C$3:$L$27,10,0)*J18,"") -> 2763 | M18: =IFERROR(VLOOKUP(B18,Stock_Data!$C$3:$M$27,11,0),"") -> 4.62 | N18: =IFERROR(I18*M18,"") -> 0.77865169 | P18: =IF(B18="","",D18) -> Insurance | Q18: =IF(B18="","",H18) -> 60000
A19: 10 | B19: UNGA | C19: =IFERROR(INDEX(Stock_Data!$B$3:$B$27,MATCH(B19,Stock_Data!$C$3:$C$27,0)),"") -> Unga Group | D19: =IFERROR(VLOOKUP(B19,Stock_Data!C12:D36,2,0),"") -> Manufacturing | E19: =IFERROR(VLOOKUP(B19,Stock_Data!$C$3:$E$27,3,0),"") -> 28 | F19: =IFERROR(VLOOKUP(B19,Screener!$C$7:$J$31,8,0),"") -> 37.99 | G19: =IFERROR(VLOOKUP(B19,Screener!$C$7:$L$31,10,0),"") -> Underperform | H19: 80000 | I19: =IFERROR(H19/SUM($H$10:$H$19),"") -> 0.2247191 | J19: =IFERROR(INT(H19/E19),"") -> 2857 | K19: =IFERROR(J19*E19,"") -> 79996 | L19: =IFERROR(VLOOKUP(B19,Stock_Data!$C$3:$L$27,10,0)*J19,"") -> 2857 | M19: =IFERROR(VLOOKUP(B19,Stock_Data!$C$3:$M$27,11,0),"") -> 3.57 | N19: =IFERROR(I19*M19,"") -> 0.80224719 | P19: =IF(B19="","",D19) -> Manufacturing | Q19: =IF(B19="","",H19) -> 80000
A21: PORTFOLIO SUMMARY
A22: Total Capital Deployed(KES): | B22: =SUM(H10:H19) -> 356000
A23: Total Current Value (KES): | B23: =SUM(K10:K19) -> 355816.2
A24: Undeployed Capital (KES): | B24: =B3 - B22 -> -256000
A25: Annual Dividend Income (KES): | B25: =SUM(L10:L19) -> 19217.7
A26: Weighted Portfolio Return (%): | B26: =SUM(N10:N19) -> 5.4026124
A27: vs Risk-Free Rate (%): | B27: =B26-B4 -> -10.097388
A28: Porfolio Rating: | B28: =IF(B27>0,"BEATS") -> FALSE

Sheet Sector_Analysis
A1: NSE SECTOR ANALYSIS Comparitive Intelligence (Dec 2024)
A3: Sector | B3: No. of Stocks | C3: Avg Price (KES) | D3: Avg P/E | E3: Avg Div Yield (%) | F3: Avg EPS Growth (%) | G3: Avg P/B | H3: Avg Composite Score | I3: Best Stock | J3: Sector Rating
A4: Banking | B4: =COUNTIF(Stock_Data!D3:D27,A4) -> 7 | C4: =AVERAGEIF(Stock_Data!D3:D27,A4,Stock_Data!E3:E27) -> 63.557143 | D4: =AVERAGEIF(Stock_Data!D3:D27,A4,Stock_Data!I3:I27) -> 5.0142857 | E4: =AVERAGEIF(Stock_Data!D3:D27,A4,Stock_Data!M3:M27) -> 7.9071429 | F4: =AVERAGEIF(Stock_Data!D3:D27,A4,Stock_Data!N3:N27) -> 5.9142857 | G4: =AVERAGEIF(Stock_Data!D3:D27,A4,Stock_Data!J3:J27) -> 70.985714 | H4: =AVERAGEIF(Screener!D7:D31,A4,Screener!J7:J31) -> 64.642143 | I4: =IFERROR(INDEX(Stock_Data!$C$3:$C$27,MATCH(_xlfn.MAXIFS(Screener!$J$7:$J$31,Screener!$D$7:$D$31,A4),Screener!$J$7:$J$31,0)),"") -> NCBA | J4: {=_xlfn.IFS(H4>=70,"Top Tier",H4>=55,"Strong",H4>=40,"Average",H4<40,"Weak")} -> Strong
A5: Telco | B5: =COUNTIF(Stock_Data!D4:D28,A5) -> 1 | C5: =AVERAGEIF(Stock_Data!D4:D28,A5,Stock_Data!E4:E28) -> 16.2 | D5: =AVERAGEIF(Stock_Data!D4:D28,A5,Stock_Data!I4:I28) -> 12.27 | E5: =AVERAGEIF(Stock_Data!D4:D28,A5,Stock_Data!M4:M28) -> 4.14 | F5: =AVERAGEIF(Stock_Data!D4:D28,A5,Stock_Data!N4:N28) -> -18.5 | G5: =AVERAGEIF(Stock_Data!D4:D28,A5,Stock_Data!J4:J28) -> 5.4 | H5: =AVERAGEIF(Screener!D8:D32,A5,Screener!J8:J32) -> 19.155 | I5: =IFERROR(INDEX(Stock_Data!$C$3:$C$27,MATCH(_xlfn.MAXIFS(Screener!$J$7:$J$31,Screener!$D$7:$D$31,A5),Screener!$J$7:$J$31,0)),"") -> SCOM | J5: {=_xlfn.IFS(H5>=70,"Top Tier",H5>=55,"Strong",H5>=40,"Average",H5<40,"Weak")} -> Weak
A6: Insurance | B6: =COUNTIF(Stock_Data!D5:D29,A6) -> 4 | C6: =AVERAGEIF(Stock_Data!D5:D29,A6,Stock_Data!E5:E29) -> 51.3375 | D6: =AVERAGEIF(Stock_Data!D5:D29,A6,Stock_Data!I5:I29) -> 8.055 | E6: =AVERAGEIF(Stock_Data!D5:D29,A6,Stock_Data!M5:M29) -> 4.7475 | F6: =AVERAGEIF(Stock_Data!D5:D29,A6,Stock_Data!N5:N29) -> -0.2 | G6: =AVERAGEIF(Stock_Data!D5:D29,A6,Stock_Data!J5:J29) -> 59.6 | H6: =AVERAGEIF(Screener!D9:D33,A6,Screener!J9:J33) -> 46.81125 | I6: =IFERROR(INDEX(Stock_Data!$C$3:$C$27,MATCH(_xlfn.MAXIFS(Screener!$J$7:$J$31,Screener!$D$7:$D$31,A6),Screener!$J$7:$J$31,0)),"") -> KNRE | J6: {=_xlfn.IFS(H6>=70,"Top Tier",H6>=55,"Strong",H6>=40,"Average",H6<40,"Weak")} -> Average
A7: Manufacturing | B7: =COUNTIF(Stock_Data!D6:D30,A7) -> 5 | C7: =AVERAGEIF(Stock_Data!D6:D30,A7,Stock_Data!E6:E30) -> 125.6 | D7: =AVERAGEIF(Stock_Data!D6:D30,A7,Stock_Data!I6:I30) -> 9.08 | E7: =AVERAGEIF(Stock_Data!D6:D30,A7,Stock_Data!M6:M30) -> 7.364 | F7: =AVERAGEIF(Stock_Data!D6:D30,A7,Stock_Data!N6:N30) -> -3.74 | G7: =AVERAGEIF(Stock_Data!D6:D30,A7,Stock_Data!J6:J30) -> 43.76 | H7: =AVERAGEIF(Screener!D10:D34,A7,Screener!J10:J34) -> 38.55 | I7: =IFERROR(INDEX(Stock_Data!$C$3:$C$27,MATCH(_xlfn.MAXIFS(Screener!$J$7:$J$31,Screener!$D$7:$D$31,A7),Screener!$J$7:$J$31,0)),"") -> BERG | J7: {=_xlfn.IFS(H7>=70,"Top Tier",H7>=55,"Strong",H7>=40,"Average",H7<40,"Weak")} -> Weak
A8: Energy | B8: =COUNTIF(Stock_Data!D7:D31,A8) -> 4 | C8: =AVERAGEIF(Stock_Data!D7:D31,A8,Stock_Data!E7:E31) -> 11.275 | D8: =AVERAGEIF(Stock_Data!D7:D31,A8,Stock_Data!I7:I31) -> 3.86 | E8: =AVERAGEIF(Stock_Data!D7:D31,A8,Stock_Data!M7:M31) -> 6.835 | F8: =AVERAGEIF(Stock_Data!D7:D31,A8,Stock_Data!N7:N31) -> -27.275 | G8: =AVERAGEIF(Stock_Data!D7:D31,A8,Stock_Data!J7:J31) -> 12.125 | H8: =AVERAGEIF(Screener!D11:D35,A8,Screener!J11:J35) -> 57.09 | I8: =IFERROR(INDEX(Stock_Data!$C$3:$C$27,MATCH(_xlfn.MAXIFS(Screener!$J$7:$J$31,Screener!$D$7:$D$31,A8),Screener!$J$7:$J$31,0)),"") -> UMME | J8: {=_xlfn.IFS(H8>=70,"Top Tier",H8>=55,"Strong",H8>=40,"Average",H8<40,"Weak")} -> Strong
A9: Investment | B9: =COUNTIF(Stock_Data!D8:D32,A9) -> 4 | C9: =AVERAGEIF(Stock_Data!D8:D32,A9,Stock_Data!E8:E32) -> 13.9 | D9: =AVERAGEIF(Stock_Data!D8:D32,A9,Stock_Data!I8:I32) -> 7.0775 | E9: =AVERAGEIF(Stock_Data!D8:D32,A9,Stock_Data!M8:M32) -> 6.18 | F9: =AVERAGEIF(Stock_Data!D8:D32,A9,Stock_Data!N8:N32) -> -2.85 | G9: =AVERAGEIF(Stock_Data!D8:D32,A9,Stock_Data!J8:J32) -> 23.1 | H9: =AVERAGEIF(Screener!D12:D36,A9,Screener!J12:J36) -> 62.39125 | I9: =IFERROR(INDEX(Stock_Data!$C$3:$C$27,MATCH(_xlfn.MAXIFS(Screener!$J$7:$J$31,Screener!$D$7:$D$31,A9),Screener!$J$7:$J$31,0)),"") -> IMH | J9: {=_xlfn.IFS(H9>=70,"Top Tier",H9>=55,"Strong",H9>=40,"Average",H9<40,"Weak")} -> Strong

Sheet Dashboard
A1: 🇰🇪 NSE ALPHA SCREENER — Executive Dashboard (Dec 2024)
A3: STOCKS ANALYSED | E3: TOP RANKED STOCK | I3: HIGHEST SCORE | M3: PORTFOLIO RETURN | Q3: ALPHA GENERATED
A4: =COUNTA(Stock_Data!C3:C27) -> 25 | E4: =INDEX(Screener!C7:C31,MATCH(1,Screener!K7:K31,0)) -> IMH | I4: =MAX(Screener!J7:J31)&"/100" -> 91.465/100 | M4: =Portfolio_Sim!B26 -> 5.4026124 | Q4: =Portfolio_Sim!B27 -> -10.097388
A5: NSE Listed Universe | E5: Rank #1 by Composite Score | I5: Best Composite Score | M5: Weighted Annual Yield | Q5: vs Kenya T-Bill Rate
A10: Company Name | B10: Composite Score
A11: =INDEX(Screener!B3:B27,MATCH(B11,Screener!J3:J27,0)) -> NCBA Group | B11: =LARGE(Screener!J3:J27,1) -> 79.75
A12: =INDEX(Screener!B4:B28,MATCH(B12,Screener!J4:J28,0)) -> Kenya Reinsurance | B12: =LARGE(Screener!J3:J27,2) -> 74.835
A13: =INDEX(Screener!B5:B29,MATCH(B13,Screener!J5:J29,0)) -> Umeme Ltd | B13: =LARGE(Screener!J3:J27,3) -> 73.745
A14: =INDEX(Screener!B6:B30,MATCH(B14,Screener!J6:J30,0)) -> Diamond Trust Bank | B14: =LARGE(Screener!J3:J27,4) -> 66.62
A15: =INDEX(Screener!B7:B31,MATCH(B15,Screener!J7:J31,0)) -> Standard Chartered | B15: =LARGE(Screener!J3:J27,5) -> 65.825
A16: =INDEX(Screener!B8:B32,MATCH(B16,Screener!J8:J32,0)) -> Co-operative Bank | B16: =LARGE(Screener!J3:J27,6) -> 65.58
A17: =INDEX(Screener!B9:B33,MATCH(B17,Screener!J9:J33,0)) -> Stanbic Holdings | B17: =LARGE(Screener!J3:J27,7) -> 62.295
A18: =INDEX(Screener!B10:B34,MATCH(B18,Screener!J10:J34,0)) -> Crown Paints | B18: =LARGE(Screener!J3:J27,8) -> 61.305
A19: =INDEX(Screener!B11:B35,MATCH(B19,Screener!J11:J35,0)) -> KenolKobil | B19: =LARGE(Screener!J3:J27,9) -> 57.955
A24: Sector | B24: No. of Stocks
A25: Banking | B25: =COUNTIF(Stock_Data!D3:D27,A25) -> 7
A26: Telco | B26: =COUNTIF(Stock_Data!D4:D28,A26) -> 1
A27: Insurance | B27: =COUNTIF(Stock_Data!D5:D29,A27) -> 4
A28: Manufacturing | B28: =COUNTIF(Stock_Data!D6:D30,A28) -> 5
A29: Energy | B29: =COUNTIF(Stock_Data!D7:D31,A29) -> 4
A30: Investment | B30: =COUNTIF(Stock_Data!D8:D32,A30) -> 4
A41: Label | B41: Return(%)
A42: My Porfolio | B42: =Portfolio_Sim!B26 -> 5.4026124
A43: Kenya T-Bill | B43: =Assumptions!B4 -> Stephen Maina
E55: =IF(X12>X13,"Portfolio BEATS the benchmark by "&ROUND(X12-X13,1)&"%"," Portfolio TRAILS the benchmark by "&ROUND(X13-X12,1)&"%") -> Portfolio TRAILS the benchmark by 0%
A57: TOP 5 NSE STOCKS — ALPHA SCREENER PICKS
A58: Rank | B58: Company | C58: Ticker | D58: Sector | E58: Score | F58: Rating | G58: Div Yield | H58: Action
A59: 1 | B59: =INDEX(Screener!$B$7:$B$31,MATCH(1,Screener!$K$7:$K$31,0)) -> I&M Holdings | C59: =INDEX(Screener!$C$8:$C$31,MATCH(1,Screener!$K$8:$K$31,0)) -> IMH | D59: =INDEX(Screener!$D$8:$D$31,MATCH(1,Screener!$K$8:$K$31,0)) -> Investment | E59: =INDEX(Screener!$J$8:$J$31,MATCH(1,Screener!$K$8:$K$31,0)) -> 91.465 | F59: =INDEX(Screener!$L$8:$L$31,MATCH(1,Screener!$K$8:$K$31,0)) -> Strong Buy | G59: =IFERROR(VLOOKUP(C59,Stock_Data!$C$3:$M$27,11,0),"") -> 8.16 | H59: =IF(E59>=75,"Strong Buy",IF(E59>=60,"Buy","Hold")) -> Strong Buy
A60: 2 | B60: =INDEX(Screener!$B$7:$B$31,MATCH(2,Screener!$K$7:$K$31,0)) -> NCBA Group | C60: =INDEX(Screener!$C$8:$C$31,MATCH(2,Screener!$K$8:$K$31,0)) -> NCBA | D60: =INDEX(Screener!$D$8:$D$31,MATCH(2,Screener!$K$8:$K$31,0)) -> Banking | E60: =INDEX(Screener!$J$8:$J$31,MATCH(2,Screener!$K$8:$K$31,0)) -> 79.75 | F60: =INDEX(Screener!$L$8:$L$31,MATCH(2,Screener!$K$8:$K$31,0)) -> Strong Buy | G60: =IFERROR(VLOOKUP(C60,Stock_Data!$C$3:$M$27,11,0),"") -> 8.78 | H60: =IF(E60>=75,"Strong Buy",IF(E60>=60,"Buy","Hold")) -> Strong Buy
A61: 3 | B61: =INDEX(Screener!$B$7:$B$31,MATCH(3,Screener!$K$7:$K$31,0)) -> Kenya Reinsurance | C61: =INDEX(Screener!$C$8:$C$31,MATCH(3,Screener!$K$8:$K$31,0)) -> KNRE | D61: =INDEX(Screener!$D$8:$D$31,MATCH(3,Screener!$K$8:$K$31,0)) -> Insurance | E61: =INDEX(Screener!$J$8:$J$31,MATCH(3,Screener!$K$8:$K$31,0)) -> 74.835 | F61: =INDEX(Screener!$L$8:$L$31,MATCH(3,Screener!$K$8:$K$31,0)) -> Buy | G61: =IFERROR(VLOOKUP(C61,Stock_Data!$C$3:$M$27,11,0),"") -> 8.7 | H61: =IF(E61>=75,"Strong Buy",IF(E61>=60,"Buy","Hold")) -> Buy
A62: 4 | B62: =INDEX(Screener!$B$7:$B$31,MATCH(4,Screener!$K$7:$K$31,0)) -> Umeme Ltd | C62: =INDEX(Screener!$C$8:$C$31,MATCH(4,Screener!$K$8:$K$31,0)) -> UMME | D62: =INDEX(Screener!$D$8:$D$31,MATCH(4,Screener!$K$8:$K$31,0)) -> Energy | E62: =INDEX(Screener!$J$8:$J$31,MATCH(4,Screener!$K$8:$K$31,0)) -> 73.745 | F62: =INDEX(Screener!$L$8:$L$31,MATCH(4,Screener!$K$8:$K$31,0)) -> Buy | G62: =IFERROR(VLOOKUP(C62,Stock_Data!$C$3:$M$27,11,0),"") -> 11.76 | H62: =IF(E62>=75,"Strong Buy",IF(E62>=60,"Buy","Hold")) -> Buy
A63: 5 | B63: =INDEX(Screener!$B$7:$B$31,MATCH(5,Screener!$K$7:$K$31,0)) -> Nation Media Group | C63: =INDEX(Screener!$C$8:$C$31,MATCH(5,Screener!$K$8:$K$31,0)) -> NMG | D63: =INDEX(Screener!$D$8:$D$31,MATCH(5,Screener!$K$8:$K$31,0)) -> Investment | E63: =INDEX(Screener!$J$8:$J$31,MATCH(5,Screener!$K$8:$K$31,0)) -> 71.24 | F63: =INDEX(Screener!$L$8:$L$31,MATCH(5,Screener!$K$8:$K$31,0)) -> Buy | G63: =IFERROR(VLOOKUP(C63,Stock_Data!$C$3:$M$27,11,0),"") -> 8.11 | H63: =IF(E63>=75,"Strong Buy",IF(E63>=60,"Buy","Hold")) -> Buy

Sheet Assumptions
A1: MODEL ASSUMPTIONS & METHODOLOGY
A3: MODEL VERSION | B3: NSE Alpha Screener v1.0
A4: Built By | B4: Stephen Maina
A5: Data AS AT | B5: 45627
A6: Data Sources | B6: NSE,Investing.com,African Markets
A8: SCORING WEIGHTS
A9: P/E Ratio Weight | B9: 0.25
A10: Dividend Yield Weight | B10: 0.2
A11: EPS Growth Weight | B11: 0.2
A12: P/B Ratio Weight | B12: 0.2
A13: Momentum Weight | B13: 0.15
A14: TOTAL | B14: =SUM(B9:B13) -> 1
A16: PORTFOLIO SETTINGS
A17: Starting Capital (KES) | B17: 100000
A18: Risk_Free Rate | B18: 0.155
A19: Investment Horizon (Years) | B19: 3
A21: RATING THRESHOLDS
A22: Strong Buy | B22: Score >75
A23: Buy | B23: Score 60-74
A24: Hold | B24: Score 45-59
A25: Underperform | B25: Score 30-44
A26: Avoid | B26: Score < 30
